{"chunk_definitions":[{"row":12,"row_count":1,"visible":true,"expansion_state":0,"options":{"engine":"r","label":"setup","include":false},"document_id":"6EE011EE","chunk_id":"csetup_chunk","chunk_label":"setup"},{"row":43,"row_count":1,"visible":true,"expansion_state":0,"options":{"engine":"r","label":"unnamed-chunk-1"},"document_id":"6EE011EE","chunk_id":"c94dr17178no7","chunk_label":"unnamed-chunk-1"},{"row":62,"row_count":1,"visible":true,"expansion_state":1,"options":{"engine":"r","label":"unnamed-chunk-3"},"document_id":"6EE011EE","chunk_id":"cun2lhetyn2ry","chunk_label":"unnamed-chunk-2"},{"row":98,"row_count":1,"visible":true,"expansion_state":0,"options":{"engine":"r","label":"unnamed-chunk-7"},"document_id":"6EE011EE","chunk_id":"c4vfn9y2h35eg","chunk_label":"unnamed-chunk-3"},{"row":117,"row_count":1,"visible":true,"expansion_state":0,"options":{"engine":"r","label":"unnamed-chunk-12"},"document_id":"6EE011EE","chunk_id":"cj5c5znya6tgx","chunk_label":"unnamed-chunk-4"},{"row":131,"row_count":1,"visible":true,"expansion_state":0,"options":{"engine":"r","label":"unnamed-chunk-11"},"document_id":"6EE011EE","chunk_id":"ca5940rk1yzbw","chunk_label":"unnamed-chunk-5"}],"doc_write_time":1692013205}